eva_sub_cli/__init__.py
eva_sub_cli/_version.py
eva_sub_cli/auth.py
eva_sub_cli/date_utils.py
eva_sub_cli/file_utils.py
eva_sub_cli/metadata.py
eva_sub_cli/orchestrator.py
eva_sub_cli/report.py
eva_sub_cli/semantic_metadata.py
eva_sub_cli/submission_ws.py
eva_sub_cli/submit.py
eva_sub_cli/utils.py
eva_sub_cli/etc/EVA_Submission_Example.xlsx
eva_sub_cli/etc/EVA_Submission_template.xlsx
eva_sub_cli/etc/eva-biosamples.json
eva_sub_cli/etc/eva_logo.png
eva_sub_cli/etc/eva_schema.json
eva_sub_cli/etc/spreadsheet2json_conf.yaml
eva_sub_cli/etc/spreadsheet2json_conf_V2.yaml
eva_sub_cli/exceptions/__init__.py
eva_sub_cli/exceptions/invalid_file_type_exception.py
eva_sub_cli/exceptions/metadata_template_version_exception.py
eva_sub_cli/exceptions/submission_not_found_exception.py
eva_sub_cli/exceptions/submission_status_exception.py
eva_sub_cli/exceptions/submission_upload_exception.py
eva_sub_cli/executables/__init__.py
eva_sub_cli/executables/check_fasta_insdc.py
eva_sub_cli/executables/check_metadata_semantics.py
eva_sub_cli/executables/cli.py
eva_sub_cli/executables/evidence_type_checker.py
eva_sub_cli/executables/samples_checker.py
eva_sub_cli/executables/trim_down.py
eva_sub_cli/executables/xlsx2json.py
eva_sub_cli/jinja_templates/html/fasta_check.html
eva_sub_cli/jinja_templates/html/file_validation.html
eva_sub_cli/jinja_templates/html/metadata_validation.html
eva_sub_cli/jinja_templates/html/project_details.html
eva_sub_cli/jinja_templates/html/report.html
eva_sub_cli/jinja_templates/html/sample_name_check.html
eva_sub_cli/jinja_templates/html/shallow_validation.html
eva_sub_cli/jinja_templates/text/fasta_check.txt
eva_sub_cli/jinja_templates/text/file_validation.txt
eva_sub_cli/jinja_templates/text/metadata_validation.txt
eva_sub_cli/jinja_templates/text/project_details.txt
eva_sub_cli/jinja_templates/text/report.txt
eva_sub_cli/jinja_templates/text/sample_name_check.txt
eva_sub_cli/jinja_templates/text/shallow_validation.txt
eva_sub_cli/nextflow/validation.nf
eva_sub_cli-0.5.2.dist-info/licenses/LICENSE
eva_sub_cli-0.5.2.dist-info/METADATA
eva_sub_cli-0.5.2.dist-info/WHEEL
eva_sub_cli-0.5.2.dist-info/entry_points.txt
eva_sub_cli-0.5.2.dist-info/top_level.txt
eva_sub_cli-0.5.2.dist-info/RECORD
