Metadata-Version: 2.4
Name: eva_sub_cli
Version: 0.5.2
Summary: EBI EVA - validation and submission command line tool
Classifier: Development Status :: 5 - Production/Stable
Classifier: Environment :: Console
Classifier: Intended Audience :: Science/Research
Classifier: Natural Language :: English
Classifier: Operating System :: POSIX :: Linux
Classifier: Operating System :: MacOS :: MacOS X
Classifier: Programming Language :: Python :: 3.6
Classifier: Programming Language :: Python :: 3.7
Classifier: Programming Language :: Python :: 3.8
Classifier: Programming Language :: Python :: 3.9
Classifier: Programming Language :: Python :: 3.10
Classifier: Topic :: Scientific/Engineering :: Bio-Informatics
Classifier: Topic :: Communications :: File Sharing
Classifier: License :: OSI Approved :: Apache Software License
Requires-Python: >=3.6
License-File: LICENSE
Requires-Dist: ebi_eva_common_pyutils==0.*,>=0.7.4
Requires-Dist: jinja2==3.*,>=3.0.0
Requires-Dist: jsonschema==4.*
Requires-Dist: openpyxl==3.*
Requires-Dist: pyyaml==6.*
Requires-Dist: pysam==0.*,>=0.23.3
Requires-Dist: requests==2.*
Requires-Dist: packaging==24.*
Requires-Dist: setuptools-scm
Dynamic: license-file
